livedesignadmin/__init__.py
livedesignadmin-0.0.1.dist-info/METADATA
livedesignadmin-0.0.1.dist-info/WHEEL
livedesignadmin-0.0.1.dist-info/top_level.txt
livedesignadmin-0.0.1.dist-info/RECORD
