Metadata-Version: 2.1
Name: livedesignadmin
Version: 0.0.1
Summary: livedesignadmin
Home-page: https://github.com/schrodinger/
Author: Andy Martin
Author-email: andy.martin@schrodinger.com
License: UNKNOWN
Platform: UNKNOWN
